MANIFEST.in
NEWS.txt
README.rst
setup.py
src/setuptools_ci.egg-info/PKG-INFO
src/setuptools_ci.egg-info/SOURCES.txt
src/setuptools_ci.egg-info/dependency_links.txt
src/setuptools_ci.egg-info/entry_points.txt
src/setuptools_ci.egg-info/not-zip-safe
src/setuptools_ci.egg-info/requires.txt
src/setuptools_ci.egg-info/top_level.txt
src/setuptools_continuousintegration/__init__.py
src/setuptools_continuousintegration/setuptools_command.py