Metadata-Version: 1.0
Name: setuptools-ci
Version: 0.1
Summary: Adds everything for continuous integration
Home-page: https://github.com/johnnoone/setuptools-ci
Author: Xavier Barbosa
Author-email: UNKNOWN
License: BSD
Keywords: continuous-integration setuptools command
Platform: UNKNOWN
Classifier: Topic :: Documentation
Classifier: Framework :: Setuptools Plugin
Classifier: Development Status :: 4 - Beta
Classifier: Programming Language :: Python
Classifier: Intended Audience :: Developers
Classifier: Operating System :: OS Independent
Classifier: License :: OSI Approved :: BSD License
Classifier: Topic :: Software Development :: Documentation
Classifier: Topic :: Software Development :: Libraries :: Python Modules
